yolo_inference/__init__.py
yolo_inference/detect.py
yolo_inference/export.py
yolo_inference/models/__init__.py
yolo_inference/models/common.py
yolo_inference/models/experimental.py
yolo_inference/models/tf.py
yolo_inference/models/yolo.py
yolo_inference/utils/__init__.py
yolo_inference/utils/activations.py
yolo_inference/utils/augmentations.py
yolo_inference/utils/autoanchor.py
yolo_inference/utils/autobatch.py
yolo_inference/utils/callbacks.py
yolo_inference/utils/dataloaders.py
yolo_inference/utils/downloads.py
yolo_inference/utils/general.py
yolo_inference/utils/loss.py
yolo_inference/utils/metrics.py
yolo_inference/utils/plots.py
yolo_inference/utils/torch_utils.py
yolo_inference/utils/triton.py
yolo_inference/utils/aws/__init__.py
yolo_inference/utils/aws/resume.py
yolo_inference/utils/loggers/__init__.py
yolo_inference/utils/loggers/clearml/__init__.py
yolo_inference/utils/loggers/clearml/clearml_utils.py
yolo_inference/utils/loggers/clearml/hpo.py
yolo_inference/utils/loggers/comet/__init__.py
yolo_inference/utils/loggers/comet/comet_utils.py
yolo_inference/utils/loggers/comet/hpo.py
yolo_inference/utils/loggers/wandb/__init__.py
yolo_inference/utils/loggers/wandb/log_dataset.py
yolo_inference/utils/loggers/wandb/sweep.py
yolo_inference/utils/loggers/wandb/wandb_utils.py
yolo_inference/utils/segment/__init__.py
yolo_inference/utils/segment/augmentations.py
yolo_inference/utils/segment/dataloaders.py
yolo_inference/utils/segment/general.py
yolo_inference/utils/segment/loss.py
yolo_inference/utils/segment/metrics.py
yolo_inference/utils/segment/plots.py
yolo_inference-2.0.2.dist-info/METADATA
yolo_inference-2.0.2.dist-info/WHEEL
yolo_inference-2.0.2.dist-info/top_level.txt
yolo_inference-2.0.2.dist-info/RECORD
