Metadata-Version: 2.2
Name: yolo_inference
Version: 2.0.2
Summary: A YOLO-based inference library for object detection, providing easy-to-use APIs for loading models and performing inference on images.
Author: Shubham Nayak
Author-email: sn85076@outlook.com
Classifier: Programming Language :: Python :: 3
Classifier: License :: OSI Approved :: MIT License
Classifier: Operating System :: OS Independent
Requires-Python: >=3.6
Requires-Dist: torch
Requires-Dist: numpy
Requires-Dist: opencv-python
Requires-Dist: Pillow
Requires-Dist: requests
Requires-Dist: tqdm
Requires-Dist: ipython
Dynamic: author
Dynamic: author-email
Dynamic: classifier
Dynamic: description
Dynamic: description-content-type
Dynamic: requires-dist
Dynamic: requires-python
Dynamic: summary
